Workbook

Sheet 📖 Asumsi Rantai Pasok
A1: 📖 PANDUAN RANTAI PASOK PERIKANAN — Aktivitas yang Menggunakan Listrik per Ton Ikan
B3: Tabel ini merangkum SEMUA aktivitas yang mengonsumsi listrik dalam rantai pasok ikan di desa perikanan, dari penangkapan hingga penjualan. Angka dalam kWh/ton ikan TERJUAL (bukan diproduksi). Gunakan sebagai referensi mengisi kalkulator di sheet berikutnya.
B5: Fase | C5: Aktivitas | D5: Kisaran Rendah (kWh/ton ikan) | E5: Nilai Tengah (kWh/ton ikan) | F5: Kisaran Tinggi (kWh/ton ikan) | G5: Sumber & Catatan
B6: FASE 1: PRA-PENANGKAPAN
B7: AP1 | C7: Pengisian daya baterai perahu listrik (Electric boat charging) | D7: 80 | E7: =AVERAGE(D7,F7) | F7: 200 | G7: Basis: motor 3–5 kW × 6 jam/trip ÷ 150 kg tangkapan/trip. Sumber: SEAFDEC (2022) 'Electric Fishing Boats in SE Asia'; FAO (2023) 'Decarbonising Small-Scale Fisheries'. Catatan: variasi tinggi tergantung efisiensi motor & jarak melaut.
B8: AP2 (opt.) | C8: Lampu pancing / fish attractor LED (Lampu LED untuk atraktor ikan) | D8: 10 | E8: =AVERAGE(D8,F8) | F8: 30 | G8: Basis: 2×50W LED × 6 jam/trip ÷ 150 kg tangkapan. Sumber: SEAFDEC (2019) 'LED Fishing Lights'; WorldFish (2021). Catatan: tidak semua perahu menggunakan lampu pancing.
B9: AP3 (opt.) | C9: Peralatan navigasi & fish finder (Sonar / GPS / echosounder) | D9: 3 | E9: =AVERAGE(D9,F9) | F9: 12 | G9: Basis: 50–100W perangkat × 6 jam/trip ÷ 150 kg. Sumber: FAO (2020) 'Fishing Vessel Equipment Energy Use'. Catatan: umumnya kecil; relevan untuk kapal >5 GT.
B10: FASE 2: PENDARATAN & PELELANGAN (TPI)
B11: AP4 | C11: Penerangan dermaga & TPI (Lighting at landing site & fish auction) | D11: 5 | E11: =AVERAGE(D11,F11) | F11: 15 | G11: Basis: overhead listrik TPI 50 kWh/hari ÷ 6 ton throughput/hari. Sumber: KKP RI (2021) 'Standar Operasional TPI'; FAO (2014) 'Infrastructure for Small-Scale Fisheries'. Catatan: amortisasi per ton tergantung volume TPI.
B12: AP5 | C12: Timbangan & conveyor sortir (Weighing & sorting equipment) | D12: 2 | E12: =AVERAGE(D12,F12) | F12: 8 | G12: Basis: ~0.5 kWh per ton untuk operasi timbang-sortir mekanis. Sumber: FAO Fisheries Technical Paper No. 506 (2007). Catatan: jika masih manual, bisa 0; angka ini untuk sistem mekanis.
B13: FASE 3: PENANGANAN & PENDINGINAN
B14: AP6 | C14: Mesin pembuat es (Ice making machine) | D14: 90 | E14: =AVERAGE(D14,F14) | F14: 110 | G14: Basis: 100 kWh/ton es × rasio 1:1 es:ikan. Sumber: FAO (2005) 'Ice in Fisheries' (FAO Fisheries Technical Paper 331); ASHRAE Refrigeration Handbook (2018). Catatan: standar industri ~90–110 kWh per ton es produksi.
B15: AP7 | C15: Cold storage / penyimpanan dingin (Chilled storage –18 °C) | D15: =25 | E15: =AVERAGE(D15,F15)*2.5 | F15: =65 | G15: Basis: 5 kWh/ton/hari × rata-rata 5–8 hari penyimpanan per ton ikan. Sumber: FAO (2005) 'Ice in Fisheries'; IIR (Int'l Institute of Refrigeration) 'Refrigerated Storage of Perishables' (2016). Catatan: jika frozen storage (−18°C), kalikan 2–2.5×.
B16: AP8 (opt.) | C16: Blast freezing / pembekuan cepat (Blast freezer, −35 °C) | D16: 120 | E16: =AVERAGE(D16,F16) | F16: 240 | G16: Basis: 15–20 kWh/ton/hari × 8–12 hari (frozen). Sumber: IIR (2016); ASHRAE (2018). Catatan: hanya relevan jika KDKMP menjual ikan beku (frozen fish), bukan segar.
B17: FASE 4: PENGOLAHAN IKAN (OPSIONAL — jika ada nilai tambah)
B18: AP9 (opt.) | C18: Mesin fillet & pemotong (Electric filleting & cutting machine) | D18: 8 | E18: =AVERAGE(D18,F18) | F18: 25 | G18: Basis: mesin fillet 2–3 kW × 2 jam/ton ikan diproses. Sumber: FAO (2014) 'Fish Processing Technology'; WorldFish (2021) 'Small-Scale Fish Processing'. Catatan: hanya jika ikan dijual dalam bentuk fillet, bukan utuh.
B19: AP10 (opt.) | C19: Mesin pengering ikan elektrik (Electric fish dryer / heat pump dryer) | D19: 300 | E19: =AVERAGE(D19,F19) | F19: 800 | G19: Basis: 400–800 kWh/ton ikan segar untuk menghasilkan ikan kering (kandungan air turun ~70%). Sumber: FAO (2013) 'Solar Drying vs Electric Drying'; UNIDO (2019) 'Energy Efficiency in Fish Processing'. PERINGATAN: nilai sangat tinggi — hanya masukkan jika produk utama adalah ikan kering.
B20: AP11 (opt.) | C20: Mesin pengalengan / vakum (Canning / vacuum packing machine) | D20: 20 | E20: =AVERAGE(D20,F20) | F20: 55 | G20: Basis: 30–50 kWh/ton untuk operasi vakum dan sealing. Sumber: FAO (2014); UNIDO (2019). Catatan: relevan untuk KDKMP yang menjual produk olahan/kemasan.
B21: FASE 5: AIR BERSIH, SANITASI & FASILITAS PENDUKUNG
B22: AP12 | C22: Pompa air bersih (Water pump for cleaning & processing) | D22: 2 | E22: =AVERAGE(D22,F22) | F22: 7 | G22: Basis: 3 m³ air per ton ikan × 0.5–1 kWh/m³ untuk pompa. Sumber: FAO (2007) 'Water Use in Fish Processing'; Generic pump energy calculation (0.5 kWh/m³ for centrifugal pump at 20m head).
B23: AP13 | C23: Sistem air laut / aerasi kolam (Seawater pump / aeration for live fish) | D23: 10 | E23: =AVERAGE(D23,F23) | F23: 35 | G23: Basis: aerator 0.5–1 kW × 8–16 jam/hari untuk kolam penampungan ikan hidup. Sumber: FAO (2012) 'Live Fish Handling'; WorldFish (2020). Catatan: hanya jika KDKMP menjual ikan hidup atau memiliki kolam penampungan.
B24: AP14 | C24: Penerangan fasilitas pengolahan (Processing facility lighting) | D24: 3 | E24: =AVERAGE(D24,F24) | F24: 10 | G24: Basis: overhead penerangan 30 kWh/hari ÷ 6 ton throughput/hari. Sumber: SNI 03-6197-2011 (Standar Pencahayaan Kerja Indonesia); IEA (2020) 'Energy Efficiency in Food Processing'.
B25: FASE 6: DISTRIBUSI & PENJUALAN
B26: AP15 | C26: Kendaraan distribusi berpendingin (Refrigerated electric delivery vehicle) | D26: 15 | E26: =AVERAGE(D26,F26) | F26: 40 | G26: Basis: 0.3 kWh/km × 50–80 km/trip, per 1 ton muatan. Sumber: IEA (2022) 'Electric Vehicles for Last-Mile Delivery'; IRENA (2021) 'Electrification of Transport for Fisheries'. Catatan: hanya jika KDKMP menggunakan armada listrik sendiri.
B27: AP16 (opt.) | C27: Display chiller di kios/pasar (Retail display chiller) | D27: 8 | E27: =AVERAGE(D27,F27) | F27: 22 | G27: Basis: chiller display 200W × 8 jam/hari per ~500 kg ikan/minggu. Sumber: ASHRAE (2018) Commercial Refrigeration; Catatan: relevan jika KDKMP memiliki kios penjualan sendiri.
B29: 📌 PENTING: Untuk desa perikanan yang menjual IKAN SEGAR, aktivitas wajib adalah AP1 + AP6 + AP7 + AP12 + AP4. Aktivitas opsional ditambahkan sesuai profil nilai tambah desa. Gunakan nilai tengah (mid) sebagai baseline, lalu sensitivitas dengan low/high.

Sheet 🐟 Kalkulator Kebutuhan Listrik
A1: 🐟 KALKULATOR KEBUTUHAN LISTRIK — Desa Perikanan KDKMP
B2: 🟨 Kuning (teks biru) = INPUT — isi / ubah sesuai data desa | 🟩 Hijau = KALKULASI otomatis | Kolom F (Aktif): 1 = aktivitas ADA, 0 = tidak ada
B4: A. PROFIL DESA — Isi sel kuning
B5: Parameter | C5: Input 🟨 | D5: Kalkulasi 🟩 | E5: Unit | F5: — | G5: Description
B6: Jumlah rumah tangga (KK) | C6: =200 | E6: KK | G6: Jumlah kepala keluarga anggota koperasi | H6: studi kasus slide kemenkop 200 KK
B7: Target konsumsi listrik harian per rumah tangga | C7: 3.4 | E7: kWh/hari/KK | G7: Minimal Tier 4 MTF ESMAP
B8: Kebutuhan listrik tahunan per rumah tangga | C8: =C7*365 | E8: kWh/tahun/KK | G8: ← KALKULASI: target konsumsi listrik per hari * 365 hari
B9: Tipe komoditas | C9: Fish | E9: — | G9: Komoditas utama yang dijual
B10: Unit komoditas | C10: ton | E10: — | G10: Satuan komoditas
B11: Total target profit bersih tahunan dari ikan | C11: =1660/2 | E11: juta Rp/thn | G11: Slide kemenkop, jual ikan 1.66 miliar pendapatan, asumsi profit margin 50%, idealnya dipasang sesuai potensi pasar
B12: Profit bersih per ton ikan | C12: 7.5 | E12: juta Rp/ton | G12: Margin bersih per ton ikan terjual
B13: Target produksi ikan (ton/tahun) | C13: =C11/C12 | E13: ton/thn | G13: ← KALKULASI: target pendapatan ÷ profit/ton
B14: Tipe komoditas 2 | C14: Ice | E14: — | G14: Komoditas sampingan yang dijual
B15: Unit komoditas 2 | C15: ton | E15: — | G15: Satuan komoditas
B16: Total target profit bersih tahunan dari es | C16: =2190/2 | E16: juta Rp/thn | G16: Slide kemenkop, jual es 2.19 miliar pendapatan, asumsi profit margin 50%, idealnya dipasang sesuai potensi pasar | H16: harus diganti manual kalau target profit ikan membuat kebutuhan es untuk ikan jadi tinggi
B17: Profit bersih per ton komoditas es | C17: 0.5 | E17: juta Rp/ton | G17: Margin bersih per ton es terjual
B18: Target produksi es (ton/tahun) | C18: =C16/C17 | E18: ton/thn | G18: ← KALKULASI: target pendapatan ÷ profit/ton
B19: Target produksi es (ton/hari) | C19: =C18/365 | E19: ton/hari | G19: crosscheck dengan slide kemenkop ice maker 4 ton/hari
B20: Kebutuhan es per tahun untuk ikan | C20: =C13*(1/1) | E20: ton/thn | G20: asumsi kebutuhan ton es:ikan = 1:1
B21: Kebutuhan es per tahun non ikan (dijual) | C21: =C18-C20 | E21: ton/thn | G21: target produksi es/tahun - kebutuhan es untuk ikan
B22: Profit bersih tahunan dari jual es ke anggota | C22: =C20*C17 | E22: juta Rp/thn | G22: kebutuhan es/tahun untuk anggota * profit es
B23: Profit bersih tahunan dari jual es ke luar | C23: =C17*C21 | E23: juta Rp/thn | G23: kebutuhan es/tahun untuk jual ke luar * profit es
B25: B. AKTIVITAS RANTAI PASOK — kWh/ton: isi sesuai profil desa (lihat sheet 📖 untuk referensi)
B26: ID Aktivitas | C26: Nama Aktivitas | D26: kWh / ton ikan 🟨 (input) | E26: kWh / tahun 🟩 (kalkulasi) | F26: Aktif? 🟨 1=Ya / 0=Tdk | G26: Sumber Referensi
B27: ── FASE 1: PRA-PENANGKAPAN
B28: AP1 | C28: Pengisian daya baterai perahu listrik | D28: ='📖 Asumsi Rantai Pasok'!E7 | E28: =D28*C13*F28 | F28: 1 | G28: SEAFDEC (2022); FAO (2023) — kisaran 80–200 kWh/ton
B29: AP2 | C29: Lampu LED pancing / fish attractor (opsional) | D29: ='📖 Asumsi Rantai Pasok'!E8 | E29: =D29*C13*F29 | F29: 1 | G29: SEAFDEC (2019); WorldFish (2021) — kisaran 10–30 kWh/ton
B30: AP3 | C30: Navigasi & fish finder (opsional) | D30: ='📖 Asumsi Rantai Pasok'!E9 | E30: =D30*C13*F30 | F30: 0 | G30: FAO (2020) — kisaran 3–12 kWh/ton
B31: ── FASE 2: PENDARATAN & PELELANGAN (TPI)
B32: AP4 | C32: Penerangan dermaga & TPI | D32: ='📖 Asumsi Rantai Pasok'!E11 | E32: =D32*C13*F32 | F32: 1 | G32: KKP RI (2021); FAO (2014) — kisaran 5–15 kWh/ton
B33: AP5 | C33: Timbangan & conveyor sortir | D33: ='📖 Asumsi Rantai Pasok'!E12 | E33: =D33*C13*F33 | F33: 1 | G33: FAO Technical Paper 506 (2007) — kisaran 2–8 kWh/ton
B34: ── FASE 3: PENANGANAN & PENDINGINAN
B35: AP6 | C35: Mesin pembuat es | D35: ='📖 Asumsi Rantai Pasok'!E14 | E35: =D35*C13*F35 | F35: 1 | G35: FAO (2005) 'Ice in Fisheries'; ASHRAE (2018) — kisaran 80–140 kWh/ton
B36: AP7 | C36: Cold storage / penyimpanan dingin (–18°C) | D36: ='📖 Asumsi Rantai Pasok'!E15 | E36: =D36*C13*F36 | F36: 1 | G36: FAO (2005); IIR (2016) — kisaran 25–65 kWh/ton. Catatan: jika frozen storage (−18°C), kalikan 2–2.5×.
B37: AP8 | C37: Blast freezing −35°C (opsional — ikan beku) | D37: ='📖 Asumsi Rantai Pasok'!E16 | E37: =D37*C13*F37 | F37: 0 | G37: IIR (2016); ASHRAE (2018) — kisaran 120–240 kWh/ton
B38: ── FASE 4: PENGOLAHAN (OPSIONAL — nilai tambah)
B39: AP9 | C39: Mesin fillet & pemotong (opsional) | D39: ='📖 Asumsi Rantai Pasok'!E18 | E39: =D39*C13*F39 | F39: 0 | G39: FAO (2014); WorldFish (2021) — kisaran 8–25 kWh/ton
B40: AP10 | C40: Mesin pengering ikan elektrik (opsional) | D40: ='📖 Asumsi Rantai Pasok'!E19 | E40: =D40*C13*F40 | F40: 0 | G40: FAO (2013); UNIDO (2019) — kisaran 300–800 kWh/ton ⚠️ TINGGI
B41: AP11 | C41: Mesin pengalengan / vakum (opsional) | D41: ='📖 Asumsi Rantai Pasok'!E20 | E41: =D41*C13*F41 | F41: 0 | G41: FAO (2014); UNIDO (2019) — kisaran 20–55 kWh/ton
B42: ── FASE 5: AIR BERSIH & FASILITAS PENDUKUNG
B43: AP12 | C43: Pompa air bersih | D43: ='📖 Asumsi Rantai Pasok'!E22 | E43: =D43*C13*F43 | F43: 1 | G43: FAO (2007); generic pump calc — kisaran 2–7 kWh/ton
B44: AP13 | C44: Aerasi kolam ikan hidup (opsional) | D44: ='📖 Asumsi Rantai Pasok'!E23 | E44: =D44*C13*F44 | F44: 0 | G44: FAO (2012); WorldFish (2020) — kisaran 10–35 kWh/ton
B45: AP14 | C45: Penerangan fasilitas pengolahan | D45: ='📖 Asumsi Rantai Pasok'!E24 | E45: =D45*C13*F45 | F45: 1 | G45: SNI 03-6197-2011; IEA (2020) — kisaran 3–10 kWh/ton
B46: ── FASE 6: DISTRIBUSI & PENJUALAN
B47: AP15 | C47: Kendaraan distribusi berpendingin (opsional) | D47: ='📖 Asumsi Rantai Pasok'!D26 | E47: =D47*C13*F47 | F47: 0 | G47: IEA (2022); IRENA (2021) — kisaran 15–40 kWh/ton
B48: AP16 | C48: Display chiller di kios/pasar (opsional) | D48: ='📖 Asumsi Rantai Pasok'!D27 | E48: =D48*C13*F48 | F48: 0 | G48: ASHRAE (2018) Commercial Refrigeration — kisaran 8–22 kWh/ton
B50: C. RINGKASAN KEBUTUHAN LISTRIK TAHUNAN
B51: Metrik Ringkasan | C51: — | D51: Nilai 🟩 | E51: Unit | F51: — | G51: Catatan
B52: Jumlah aktivitas aktif | D52: =SUM(F28,F29,F30,F32,F33,F35,F36,F37,F39,F40,F41,F43,F44,F45,F47,F48) | E52: dari 16 | G52: Jumlah aktivitas yang ditandai 1 (aktif)
B53: kWh per ton ikan (hanya AP aktif) | D53: =SUM(D28*F28,D29*F29,D30*F30,D32*F32,D33*F33,D35*F35,D36*F36,D37*F37,D39*F39,D40*F40,D41*F41,D43*F43,D44*F44,D45*F45,D47*F47,D48*F48) | E53: kWh/ton | G53: Hanya aktivitas aktif
B54: kWh per ton es | D54: =D35*(1/1) | E54: kWh/ton | G54: asumsi kebutuhan ton es:ikan = 1:1
B55: Total kebutuhan listrik komoditas ikan per tahun (termasuk es untuk aktivitas perikanan) | D55: =D53*C13 | E55: kWh/tahun | G55: kWh/ton komoditas * target produksi
B56: Total kebutuhan listrik komoditas es per tahun (dijual untuk pihak luar selain kegiatan perikanan lokal) | D56: =D54*C21 | E56: kWh/tahun | G56: kWh/ton komoditas * target produksi
B57: Total kebutuhan listrik ekonomi produktif per tahun | D57: =SUM(D55:D56) | E57: kWh/tahun | G57: total kWh/tahun seluruh komoditas
B58: Total kebutuhan listrik rumah tangga per tahun | D58: =C6*C8 | E58: kWh/tahun | G58: kebutuhan listrik per rumah tangga * jumlah rumah tangga
B59: Total kebutuhan listrik desa per tahun | D59: =SUM(D57:D58) | E59: kWh/tahun | G59: Kebutuhan listrik rumah tangga dan ekonomi produktif
B60: Kebutuhan kapasitas PLTS indikatif | D60: =D59/(8760*0.16) | E60: kWp | G60: kWh/tahun ÷ (8760 jam/tahun x CF PLTS), asumsi CF PLTS 16%
B61: Estimasi kapasitas BESS | D61: =D60*2 | E61: kWh | G61: Rule of thumb: BESS ≈ 2× PLTS kWp → kWh, untuk fishing village
B62: Target kapasitas PLTS (oversized) | D62: 1000 | E62: kWp | G62: kalau ada target, misal 1 MWp per KDKMP
B63: Kapasitas PLTS untuk Model 2 (if oversized) | D63: =IF(D60<D62,D62,D60) | E63: kWp | G63: kalau ada target, misal 1 MWp per KDKMP
B64: Oversizing (%) | D64: =(D63-D60)/D60 | E64: - | G64: ratio surplus capacity (oversized cap-kebutuhan cap)/kebutuhan cap
B65: Estimasi listrik yang diekspor ke PLN | D65: =D64*D59 | E65: kWh/tahun | G65: HANYA jika oversized PLTS

Sheet 💰 Kapasitas & Investasi
A1: 💰 KAPASITAS PERALATAN & KEBUTUHAN INVESTASI — Desa Perikanan KDKMP
B2: 🟨 Kuning (biru) = INPUT — ubah sesuai kondisi lapangan | 🟩 Hijau tua = Kalkulasi otomatis | 🟩 Hijau muda = Link dari sheet 🐟 Kalkulator | Abu-abu = Aktivitas tidak aktif (Kolom F=0 di sheet kalkulator)
B4: A. ASUMSI TEKNIS KAPASITAS — Ubah sesuai data lapangan / desain teknis
C5: Parameter Asumsi | E5: Nilai Input 🟨 | F5: Unit | G5: Description
C6: Hari operasi penangkapan ikan / tahun | E6: 200 | F6: hari/thn | G6: Jumlah hari melaut per tahun (245 hari di Indonesia bagian barat)
C7: Hari operasi pabrik es / tahun | E7: 365 | F7: hari/thn | G7: Ice maker dan cold storage beroperasi sepanjang tahun
C8: Tangkapan per kapal per trip | E8: 150 | F8: kg/trip | G8: Rata-rata tangkapan kapal kecil <5 GT; sumber: KKP 2022
C9: Trip per kapal per tahun | E9: 200 | F9: trip/thn | G9: Asumsi 1 trip/hari × hari operasi; sesuaikan dengan pola lokal
C10: Daya motor perahu per kapal | E10: 3.7 | F10: kW/kapal | G10: Setara motor 5 HP; untuk kapal <5 GT; sumber: SEAFDEC 2022
C11: Jam operasi motor perahu per trip | E11: 6 | F11: jam/trip | G11: Pergi-pulang + waktu mancing; rata-rata perairan pesisir
C12: Efisiensi drivetrain / pengisian | E12: 0.88 | F12: — | G12: Efisiensi motor listrik + pengisian baterai (0.85–0.92)
C13: Kapasitas baterai kapal (kWh/kapal) | E13: =E10*E11/E12 | F13: kWh/kapal | G13: ← KALKULASI: daya × jam / efisiensi
C14: Kapasitas unit ice maker | E14: 4 | F14: ton/hari/unit | G14: Ukuran unit ice maker yang tersedia di pasaran Indonesia
C15: Faktor buffer kapasitas ice maker | E15: 1.25 | F15: — | G15: Buffer 25% untuk puncak permintaan musim panen
C16: Lama simpan ikan di cold storage | E16: 5 | F16: hari | G16: Rata-rata 3–7 hari sebelum distribusi; sesuaikan profil penjualan
C17: Densitas penyimpanan ikan beku | E17: 0.4 | F17: ton/m³ | G17: Ikan susun dalam keranjang: 350–450 kg/m³
C18: Faktor buffer kapasitas cold storage | E18: 1.3 | F18: — | G18: Buffer 30% untuk musim puncak
C19: Kebutuhan air per ton ikan diproses | E19: 3 | F19: m³/ton | G19: Cuci + sanitasi; sumber: FAO (2007) 'Water Use in Fish Processing'
C20: Kebutuhan air per ton es diproduksi | E20: 1.1 | F20: m³/ton es | G20: Air baku untuk ice maker + susut uap; sumber: ASHRAE (2018)
C21: Luas area TPI / dermaga | E21: 200 | F21: m² | G21: Estimasi; sesuaikan dengan desain TPI aktual
C22: Luas fasilitas pengolahan | E22: 300 | F22: m² | G22: Processing + penyimpanan; sesuaikan desain
C23: Standar pencahayaan kerja (LED) | E23: 15 | F23: W/m² | G23: SNI 03-6197-2011 untuk area kerja industri makanan
C24: Jam operasi penerangan per hari | E24: 12 | F24: jam/hari | G24: Termasuk persiapan pagi dan sore setelah sunset
B27: B. KAPASITAS PERALATAN PRODUKSI — Dihitung dari target produksi & asumsi teknis
B28: ID | C28: Nama Peralatan | D28: Basis Kalkulasi Kapasitas | E28: Kapasitas 🟩 | F28: Satuan Kapasitas | G28: Daya (kW) 🟩 | H28: Jumlah Unit 🟩 | I28: Harga/Unit (Rp juta) 🟨 | J28: Total Investasi (Rp juta) 🟩 | K28: Sumber Harga & Catatan
B29: ── FASE 1: PRA-PENANGKAPAN
B30: AP1 | C30: Perahu listrik (motor + baterai + charger) | D30: Jumlah kapal = CEILING(target ikan × 1000 ÷ (tangkapan/trip × trip/thn), 1) | E30: =CEILING('🐟 Kalkulator Kebutuhan Listrik'!C13*1000/(E8*E9),1) | F30: kapal | G30: =H30*E10 | H30: =IF('🐟 Kalkulator Kebutuhan Listrik'!F28=1,CEILING('🐟 Kalkulator Kebutuhan Listrik'!C13*1000/(E8*E9),1),0) | I30: 50 | J30: =H30*I30 | K30: Rp 50 juta/kapal = konversi motor listrik Rp 15–20 jt + baterai ~25 kWh Rp 25–30 jt + charger Rp 5–8 jt. Sumber: KESDM (2023), market survey
B31: AP2 | C31: Set LED fish attractor (per kapal) | D31: Jumlah set = jumlah kapal (1 set per kapal) | E31: =CEILING('🐟 Kalkulator Kebutuhan Listrik'!C13*1000/(E8*E9),1) | F31: set/kapal | G31: =H31*0.1 | H31: =IF('🐟 Kalkulator Kebutuhan Listrik'!F29=1,CEILING('🐟 Kalkulator Kebutuhan Listrik'!C13*1000/(E8*E9),1),0) | I31: 2 | J31: =H31*I31 | K31: Rp 2 juta/set = 2×LED 50W + kabel waterproof + housing. Sumber: toko maritim Surabaya 2024
B32: AP3 | C32: Peralatan navigasi & fish finder | D32: Jumlah unit = jumlah kapal (1 unit per kapal) | E32: =CEILING('🐟 Kalkulator Kebutuhan Listrik'!C13*1000/(E8*E9),1) | F32: unit/kapal | G32: — | H32: =IF('🐟 Kalkulator Kebutuhan Listrik'!F30=1,CEILING('🐟 Kalkulator Kebutuhan Listrik'!C13*1000/(E8*E9),1),0) | I32: 5 | J32: =H32*I32 | K32: Rp 5 juta/unit = GPS chartplotter + echosounder entry-level. Sumber: toko marine electronics 2024
B33: ── FASE 2: PENDARATAN & PELELANGAN (TPI)
B34: AP4 | C34: Sistem penerangan TPI & dermaga (LED) | D34: Daya = luas TPI × standar pencahayaan ÷ 1000 | E34: =IF('🐟 Kalkulator Kebutuhan Listrik'!C13>0,E21*E23/1000,0) | F34: kW (terpasang) | G34: =E21*E23/1000 | H34: =IF('🐟 Kalkulator Kebutuhan Listrik'!C13>0,IF('🐟 Kalkulator Kebutuhan Listrik'!F32=1,CEILING((E21*E23)/36,1),0),0) | I34: 0.15 | J34: =H34*I34 | K34: Rp 0.15 juta/panel = LED panel 36W industri. Sumber: e-katalog LKPP 2024
B35: AP5 | C35: Timbangan listrik & conveyor sortir | D35: Throughput puncak/hari = target ikan/hari operasi + target es/hari | E35: =('🐟 Kalkulator Kebutuhan Listrik'!C13/E6+'🐟 Kalkulator Kebutuhan Listrik'!C19) | F35: ton/hari | G35: =H35*0.5 | H35: =IF('🐟 Kalkulator Kebutuhan Listrik'!F33=1,CEILING(('🐟 Kalkulator Kebutuhan Listrik'!C13/E6+'🐟 Kalkulator Kebutuhan Listrik'!C19)/3,1),0) | I35: 10 | J35: =H35*I35 | K35: Rp 10 juta/unit = timbangan digital 500 kg industri (merek lokal). Sumber: tokopedia industrial 2024
B36: ── FASE 3: PENANGANAN & PENDINGINAN
B37: AP6 | C37: Mesin pembuat es (ice maker) | D37: Kapasitas = target es/hari × buffer. Unit = CEILING(kap ÷ ukuran unit, 1) | E37: ='🐟 Kalkulator Kebutuhan Listrik'!C19*E15 | F37: ton es/hari | G37: =H37*E14*100/24 | H37: =IF('🐟 Kalkulator Kebutuhan Listrik'!F35=1,CEILING('🐟 Kalkulator Kebutuhan Listrik'!C19*E15/E14,1),0) | I37: 180 | J37: =H37*I37 | K37: Rp 180 juta/unit kapasitas 5 ton/hari (merek Asia, compressor Bitzer). Kisaran Rp 150–250 juta. Sumber: distributor ice machine Jakarta 2024
B38: AP7 | C38: Cold storage / ruang pendingin (-18°C) | D38: Volume = target ikan × lama simpan ÷ 365 ÷ densitas × buffer | E38: =CEILING('🐟 Kalkulator Kebutuhan Listrik'!C13*E16/365/E17*E18,1) | F38: m³ | G38: =E38*0.25 | H38: =IF('🐟 Kalkulator Kebutuhan Listrik'!F36=1,1,0) | I38: 22 | J38: =E38*I38*H38 | K38: Rp 22 juta/m³ = cold room panel prefab + compressor Danfoss, instalasi. Kisaran Rp 18–30 juta/m³. Sumber: PT Frozen Indo, market survey 2024
B39: AP8 | C39: Blast freezer −35°C (opsional — ikan beku) | D39: Volume setara cold storage; aktifkan jika produk utama frozen fish | E39: =CEILING('🐟 Kalkulator Kebutuhan Listrik'!C13*E16/365/E17*E18,1) | F39: m³ | G39: — | H39: =IF('🐟 Kalkulator Kebutuhan Listrik'!F37=1,1,0) | I39: 40 | J39: =E39*I39*H39 | K39: Rp 40 juta/m³ = blast freezer impor (Korea/China). Sumber: market survey 2024
B40: ── FASE 4: PENGOLAHAN IKAN (OPSIONAL — nilai tambah)
B41: AP9 | C41: Mesin fillet & pemotong ikan | D41: Throughput/hari = target ikan ÷ hari operasi. 1 mesin ≈ 0.5 ton/hari | E41: ='🐟 Kalkulator Kebutuhan Listrik'!C13/E6 | F41: ton/hari | G41: =IF(H41>0,H41*2,0) | H41: =IF('🐟 Kalkulator Kebutuhan Listrik'!F39=1,CEILING('🐟 Kalkulator Kebutuhan Listrik'!C13/E6/0.5,1),0) | I41: 20 | J41: =H41*I41 | K41: Rp 20 juta/unit = mesin fillet semi-otomatis kapasitas 300–500 kg/hari. Sumber: UMKM perikanan Bitung 2023
B42: AP10 | C42: Mesin pengering ikan elektrik (heat pump dryer) | D42: Kapasitas per batch; 1 ton ikan segar → 0.25 ton ikan kering | E42: ='🐟 Kalkulator Kebutuhan Listrik'!C13/E6 | F42: ton segar/hari | G42: =IF(H42>0,H42*3,0) | H42: =IF('🐟 Kalkulator Kebutuhan Listrik'!F40=1,CEILING('🐟 Kalkulator Kebutuhan Listrik'!C13/E6/0.3,1),0) | I42: 75 | J42: =H42*I42 | K42: Rp 75 juta/unit heat pump dryer kapasitas 300 kg/batch (merek lokal). Sumber: BPPT (2022)
B43: AP11 | C43: Mesin vakum / pengalengan | D43: 1 mesin = ~100 kg/jam; throughput harian = target ikan/hari | E43: ='🐟 Kalkulator Kebutuhan Listrik'!C13/E6 | F43: ton/hari | G43: =IF(H43>0,H43*0.5,0) | H43: =IF('🐟 Kalkulator Kebutuhan Listrik'!F41=1,CEILING('🐟 Kalkulator Kebutuhan Listrik'!C13/E6/1,1),0) | I43: 15 | J43: =H43*I43 | K43: Rp 15 juta/unit = mesin vakum sealer industri 300–500 pcs/jam. Sumber: tokopedia industrial 2024
B44: ── FASE 5: AIR BERSIH & FASILITAS PENDUKUNG
B45: AP12 | C45: Pompa air bersih (sentrifugal) | D45: Kebutuhan air/hari = (ikan × air/ton ÷ hari operasi) + (es/hari × air/ton es) | E45: =('🐟 Kalkulator Kebutuhan Listrik'!C13*E19/E6)+('🐟 Kalkulator Kebutuhan Listrik'!C19*E20) | F45: m³/hari | G45: =H45*0.75 | H45: =IF('🐟 Kalkulator Kebutuhan Listrik'!F43=1,CEILING(('🐟 Kalkulator Kebutuhan Listrik'!C13*E19/E6+'🐟 Kalkulator Kebutuhan Listrik'!C19*E20)/8/1.5,1),0) | I45: 5 | J45: =H45*I45 | K45: Rp 5 juta/unit = pompa sentrifugal 1–2 m³/jam, head 20m (merek Grundfos/CNP). Sumber: distributor pompa 2024
B46: AP13 | C46: Sistem aerasi kolam ikan hidup | D46: Kapasitas = volume kolam (m³); 1 unit aerator per 5 m³ | E46: =IF('🐟 Kalkulator Kebutuhan Listrik'!C13>0,20,0) | F46: m³ kolam | G46: =IF(H46>0,H46*0.75,0) | H46: =IF('🐟 Kalkulator Kebutuhan Listrik'!F44=1,CEILING(E46/5,1),0) | I46: 3 | J46: =H46*I46 | K46: Rp 3 juta/unit aerator 0.75 kW. Sumber: toko akuakultur 2024
B47: AP14 | C47: Sistem penerangan fasilitas pengolahan (LED) | D47: Daya = luas fasilitas × standar pencahayaan ÷ 1000 | E47: =IF('🐟 Kalkulator Kebutuhan Listrik'!C13>0,E22*E23/1000,0) | F47: kW (terpasang) | G47: =E47 | H47: =IF('🐟 Kalkulator Kebutuhan Listrik'!C13>0,IF('🐟 Kalkulator Kebutuhan Listrik'!F45=1,CEILING((E22*E23)/36,1),0),0) | I47: 0.15 | J47: =H47*I47 | K47: Rp 0.15 juta/panel LED 36W industri. Sumber: e-katalog LKPP 2024
B48: ── FASE 6: DISTRIBUSI & PENJUALAN
B49: AP15 | C49: Kendaraan distribusi berpendingin (EV) | D49: 1 kendaraan per ~3 ton/hari distribusi; kapasitas 1 ton/kendaraan | E49: =CEILING('🐟 Kalkulator Kebutuhan Listrik'!C19/3,1) | F49: unit kendaraan | G49: — | H49: =CEILING('🐟 Kalkulator Kebutuhan Listrik'!C19/3,1) | I49: 350 | J49: =IF('🐟 Kalkulator Kebutuhan Listrik'!F47=1,H49*I49,0) | K49: Rp 350 juta/unit EV pikap berpendingin (Rp 250–400 juta). Sumber: DFSK/Wuling distribusi 2024
B50: AP16 | C50: Display chiller kios / pasar (showcase) | D50: 1 unit per kios penjualan; default 2 kios | E50: =IF('🐟 Kalkulator Kebutuhan Listrik'!C13>0,2,0) | F50: unit | G50: — | H50: =IF('🐟 Kalkulator Kebutuhan Listrik'!F48=1,2,0) | I50: 8 | J50: =H50*I50 | K50: Rp 8 juta/unit = display chiller showcase 300L (merek GEA/Hisense). Sumber: toko peralatan resto 2024
B52: C. SUBTOTAL INVESTASI PERALATAN PRODUKSI
B53: Total investasi semua peralatan wajib aktif (Rp juta) | J53: =J30+J34+J35+J37+J38+J45+J47
B54: Total investasi peralatan opsional aktif (Rp juta) | J54: =J31+J32+J39+J41+J42+J43+J46+J49+J50
B55: TOTAL INVESTASI SELURUH PERALATAN ASET PRODUKSI (Rp juta) | J55: =SUM(J53:J54)
B57: D. INVESTASI SISTEM PLTS (Photovoltaic + BESS + Distribusi + EPC)
B58: — | C58: Komponen PLTS | D58: Basis Perhitungan | E58: Kapasitas 🟩 | F58: Unit | G58: Harga Satuan (Rp juta) 🟨 | H58: — | I58: — | J58: Total (Rp juta) 🟩 | K58: Sumber & Catatan
C59: Panel surya PLTS (modul PV) | D59: Dari 🐟 Kalkulator → kWp | E59: ='🐟 Kalkulator Kebutuhan Listrik'!D60 | F59: kWp | G59: 5.5 | J59: =E59*G59 | K59: Rp 5.5 juta/kWp hanya modul (tier-1 mono PERC 450Wp). Sumber: ESDM tender 2024, PT Len
C60: Inverter string / on-grid | D60: Dari 🐟 Kalkulator → kWp | E60: ='🐟 Kalkulator Kebutuhan Listrik'!D60 | F60: kWp | G60: 1.8 | J60: =E60*G60 | K60: Rp 1.8 juta/kWp inverter string (Huawei/SMA). Sumber: distributor PV 2024
C61: Mounting & struktur | D61: Dari 🐟 Kalkulator → kWp | E61: ='🐟 Kalkulator Kebutuhan Listrik'!D60 | F61: kWp | G61: 0.8 | J61: =E61*G61 | K61: Rp 0.8 juta/kWp mounting galvanis + ballast (atap/ground). Sumber: kontraktor EPC 2024
C62: Kabel & proteksi (BOS) | D62: Dari 🐟 Kalkulator → kWp | E62: ='🐟 Kalkulator Kebutuhan Listrik'!D60 | F62: kWp | G62: 0.5 | J62: =E62*G62 | K62: Rp 0.5 juta/kWp kabel DC/AC + combiner box + arrester + panel. Sumber: BOS benchmark 10%
C63: BESS — baterai LFP | D63: Dari 🐟 Kalkulator → kWh | E63: ='🐟 Kalkulator Kebutuhan Listrik'!D61 | F63: kWh | G63: 3.5 | J63: =E63*G63 | K63: Rp 3.5 juta/kWh baterai LFP (CATL/BYD prismatic). Kisaran Rp 3–5 juta/kWh. Sumber: IESR (2024)
C64: BESS — BMS, inverter, rack, instalasi | D64: Dari 🐟 Kalkulator → kWh | E64: ='🐟 Kalkulator Kebutuhan Listrik'!D61 | F64: kWh | G64: 1 | J64: =E64*G64 | K64: Rp 1 juta/kWh sistem manajemen + integrasi. ~25–30% dari biaya baterai
C65: Jaringan distribusi ke pengguna | D65: Dari 🐟 Kalkulator → KK | E65: ='🐟 Kalkulator Kebutuhan Listrik'!C6 | F65: KK | G65: 6 | J65: =E65*G65 | K65: Rp 6 juta/KK jaringan LV (kabel SR + tiang + MCB). Sumber: PLN distribusi benchmark 2023
C66: EPC & instalasi (jasa) | D66: Dihitung dari biaya hardware PLTS | E66: =('🐟 Kalkulator Kebutuhan Listrik'!D60*5.5+'🐟 Kalkulator Kebutuhan Listrik'!D60*1.8+'🐟 Kalkulator Kebutuhan Listrik'!D60*0.8+'🐟 Kalkulator Kebutuhan Listrik'!D60*0.5)*0.12 | F66: — | G66: 1 | J66: =E66*G66 | K66: 12% dari biaya hardware PLTS+inverter+mounting+BOS sebagai biaya EPC. Sumber: IESR rule-of-thumb
C67: Commissioning & pelatihan O&M | D67: Dihitung dari biaya hardware PLTS | E67: 1 | F67: lump sum | G67: 50 | J67: =G67 | K67: Rp 50 juta lump sum = commissioning + pelatihan teknisi KDKMP (3 hari). Sumber: expert estimate
B69: Subtotal PLTS + Inverter + Mounting + BOS (Rp juta) | J69: =J59+J60+J61+J62
B70: Subtotal BESS (Rp juta) | J70: =J63+J64
B71: Subtotal Distribusi + EPC + Commissioning (Rp juta) | J71: =J65+J66+J67
B72: TOTAL INVESTASI SISTEM PLTS (Rp juta) | J72: =SUM(J69:J71)
B74: E. RINGKASAN TOTAL KEBUTUHAN INVESTASI
B75: Total investasi peralatan produksi (hanya AP aktif) | J75: =J55
B76: Total investasi sistem PLTS + BESS + Distribusi | J76: =J72
B77: TOTAL KEBUTUHAN INVESTASI (Rp juta) | J77: =J75+J76
B78: dalam Rp miliar | J78: =J77/1000

Sheet Kalkulator Pendapatan
A1: REVENUE CALCULATOR FOR EACH BUSINESS MODEL
A2: Teks biru = INPUT — ubah sesuai kondisi lapangan | Teks hitam = Kalkulasi otomatis atau link dari sheet lain
A4: A. KDKMP Revenue from Electricity Sales
A5: - | B5: Parameter | C5: Model 1 (3rd Party IPP) | D5: Model 2 (KDKMP owns PLTS) | E5: Model 3 (KDKMP owns PLTS and Productive Assets) | F5: Notes
A6: - | B6: Tariff charged to members (Rp/kWh) | C6: 2000 | D6: 0 | E6: 2000 | F6: Rp/kWh | Set below PLN urban tariff to be competitive; survey members' WTP
A7: - | B7: Tariff paid to IPP (Rp/kWh) | C7: 1300 | D7: 0 | E7: 0 | F7: Rp/kWh | Negotiate with IPP; must give IPP ≥12% IRR on their investment, only for Model 1
A8: - | B8: PLN PJBL tariff (Rp/kWh) | C8: 0 | D8: 2000 | E8: 0 | F8: Rp/kWh | Verify against PLN regional BPP; current policy approx. Rp 800-1200
A9: - | B9: PLN tariff to end users (Rp/kWh) | C9: 0 | D9: 500 | E9: 0 | F9: Rp/kWh | Subsidised household R1 tariff; from PLN tariff schedule
A10: - | B10: PLN profit margin | C10: 0.07 | D10: 0.07 | E10: 0.07 | F10: assumption, in %
A11: - | B11: Govt subsidy to PLN (Rp/kWh) | C11: =(C8*(1+C10))-C9 | D11: =(D8*(1+D10))-D9 | E11: =(E8*(1+E10))-E9 | F11: Rp/kWh ← CALCULATED (PJBL tariff – PLN end-user tariff)
A12: - | B12: Collection efficiency | C12: 0.88 | D12: 0.88 | E12: 0.88 | F12: ratio | % of billed kWh actually collected (default loss for payment gaps)
A13: - | B13: KDKMP revenue (Rp/kWh) | C13: =C6-C7 | D13: =D8 | E13: =E6-E7 | F13: Rp/kWh ← CALCULATED (tariff charged – tariff to IPP)
A14: - | B14: Annual kWh sold to members | C14: ='🐟 Kalkulator Kebutuhan Listrik'!D57+'🐟 Kalkulator Kebutuhan Listrik'!D58 | D14: ='🐟 Kalkulator Kebutuhan Listrik'!D57+'🐟 Kalkulator Kebutuhan Listrik'!D58 | E14: ='🐟 Kalkulator Kebutuhan Listrik'!D58 | F14: kWh/yr ← LINKED from Kalkulator Desa Perikanan, Model 3 does not sell kWh for productive activities
A15: - | B15: Surplus sold to PLN grid (oversizing to 1 MWp PLTS) | C15: 0 | D15: ='🐟 Kalkulator Kebutuhan Listrik'!D65 | E15: 0 | F15: kWh/year, Oversizing to target 1 MWp per KDKMP for Model 2
A16: - | B16: Annual revenue electricity sold to members (Rp juta) | C16: =C12*C13*C14/1000000 | D16: =D12*D13*D14/1000000 | E16: =E12*E13*E14/1000000
A17: - | B17: Annual revenue electricity surplus sold to PLN (Rp juta) | C17: =C12*C13*C15/1000000 | D17: =D12*D13*D15/1000000 | E17: =E12*E13*E15/1000000 | F17: surplus from oversized PLTS
A18: - | B18: Annual Revenue KDKMP (Rp juta) | C18: =SUM(C16:C17) | D18: =SUM(D16:D17) | E18: =SUM(E16:E17) | F18: Rp juta/yr ← CALCULATED
A19: - | B19: Govt subsidy to KDKMP for PLTS inf. (Rp juta/yr) | C19: 0 | D19: 80 | E19: 80 | F19: Rp juta/yr | Operating subsidy or capital rebate — enter 0 if none
A20: - | B20: Total Annual Electricity Sales Revenue incl. subsidy (Rp juta/year) | C20: =C18+C19 | D20: =D18+D19 | E20: =E18+E19 | F20: Rp juta/yr ← CALCULATED
A22: B. KDKMP Revenue from EaaS — Energy as a Service (Model 3 Only)
A23: - | B23: Parameter | C23: Model 1 (3rd Party IPP) | D23: Model 2 (KDKMP owns PLTS) | E23: Model 3 (KDKMP owns PLTS and Productive Assets) | F23: Notes
A24: - | B24: Annual EaaS Revenue KDKMP (Rp juta) | C24: 0 | D24: 0 | E24: =H105 | F24: Rp juta/yr ← CALCULATED (fee × kWh × collection / 1,000,000)
A25: - | B25: Govt subsidy to KDKMP for EaaS inf. (Rp juta/yr) | C25: 0 | D25: 0 | E25: 0 | F25: Rp juta/yr | Enter 0 if none
A26: - | B26: Total EaaS Revenue incl. subsidy (Rp juta/yr) | C26: 0 | D26: 0 | E26: =E24+E25 | F26: Rp juta/yr ← CALCULATED
A28: C. KDKMP CAPEX Exposure by Business Model (Rp juta)
A29: - | B29: Parameter | C29: Model 1 (3rd Party IPP) | D29: Model 2 (KDKMP owns PLTS) | E29: Model 3 (KDKMP owns PLTS and Productive Assets) | F29: Notes
A30: - | B30: PLTS + BESS + Distribution CAPEX | C30: 0 | D30: =('💰 Kapasitas & Investasi'!J69*(1+'🐟 Kalkulator Kebutuhan Listrik'!D64))+'💰 Kapasitas & Investasi'!J70+'💰 Kapasitas & Investasi'!J71 | E30: ='💰 Kapasitas & Investasi'!J72 | F30: Rp juta | Model 1: PLTS owned by IPP (KDKMP=0); Models 2&3: KDKMP owns PLTS (model 2 oversized to 1 MWp)
A31: - | B31: Productive Assets CAPEX (cold storage, ice maker, boats, etc.) | C31: 0 | D31: 0 | E31: ='💰 Kapasitas & Investasi'!J55 | F31: Rp juta | Model 3 only
A32: - | B32: TOTAL KDKMP CAPEX (Rp juta) | C32: =C30+C31 | D32: =D30+D31 | E32: =E30+E31 | F32: Rp juta ← CALCULATED
A33: - | B33: Grant / Dana Hibah received (Rp juta) | C33: 0 | D33: 500 | E33: 500 | F33: Rp juta | Total grant/hibah injection; adjust per actual commitment
A34: - | B34: NET KDKMP CAPEX after Grant (Rp juta) | C34: =C32-C33 | D34: =D32-D33 | E34: =E32-E33 | F34: Rp juta ← CALCULATED = Total CAPEX - Grant
A36: D. KDKMP Annual OPEX Exposure (Rp juta/tahun)
A37: - | B37: Parameter | C37: Model 1 (3rd Party IPP) | D37: Model 2 (KDKMP owns PLTS) | E37: Model 3 (KDKMP owns PLTS and Productive Assets) | F37: Notes
A38: - | B38: PLTS O&M rate (% of PLTS CAPEX per year) | C38: 0.02 | D38: 0.02 | E38: 0.02 | F38: ratio | 1.5–2.5% industry standard
A39: - | B39: PLTS O&M Annual Cost (Rp juta/tahun) | C39: =C38*C30 | D39: =D38*D30 | E39: =E38*E30 | F39: Rp juta/yr ← CALCULATED
A40: - | B40: Productive Assets O&M rate (% of asset CAPEX/yr) | C40: 0.05 | D40: 0.05 | E40: 0.05 | F40: ratio | Cold storage, ice maker, boats: ~5%/yr maintenance
A41: - | B41: Productive Asset O&M Annual (Rp juta/tahun) | C41: =C40*C31 | D41: =D40*D31 | E41: =E40*E31 | F41: Rp juta/yr ← CALCULATED
A42: - | B42: KDKMP staff / management cost (Rp juta/tahun) | C42: 120 | D42: 120 | E42: =IF('💰 Kapasitas & Investasi'!J55>0,D42/(2/3),D42) | F42: Rp juta/yr | Model 3 needs larger team for EaaS operations (assume 1.5x more)
A43: - | B43: Total Annual OPEX (Rp juta/yr) | C43: =C39+C41+C42 | D43: =D39+D41+D42 | E43: =E39+E41+E42 | F43: Rp juta ← CALCULATED
A45: E. Annual Net Revenue & Grant Recovery
A46: - | B46: Parameter | C46: Model 1 (3rd Party IPP) | D46: Model 2 (KDKMP owns PLTS) | E46: Model 3 (KDKMP owns PLTS and Productive Assets) | F46: Notes
A47: - | B47: Total Annual Revenue (Electricity + EaaS) (Rp juta) | C47: =C20 | D47: =D20 | E47: =E20+E26 | F47: Rp juta/yr ← CALCULATED
A48: - | B48: Annual Net Income after OPEX (Rp juta/yr) | C48: =C47-C43 | D48: =D47-D43 | E48: =E47-E43 | F48: Rp juta/yr ← CALCULATED = Total Revenue - Total OPEX
A49: - | B49: Grant Recovery Ratio (% of net income allocated to grant recovery) | C49: 0.3 | D49: 0.3 | E49: 0.3 | F49: ratio | Fraction of annual net income earmarked to recover grant capital
A50: - | B50: Annual Grant Recovery Contribution (Rp juta/yr) | C50: =IF(C48>0,C48*C49,0) | D50: =IF(D48>0,D48*D49,0) | E50: =IF(E48>0,E48*E49,0) | F50: Rp juta/yr ← CALCULATED
A51: - | B51: Estimated Years to Full Grant Recovery | C51: =IFERROR(IF(C50>0,C34/C50,"N/A"),"N/A") | D51: =IFERROR(IF(D50>0,D34/D50,"N/A"),"N/A") | E51: =IFERROR(IF(E50>0,E34/E50,"N/A"),"N/A") | F51: years ← Net CAPEX after grant ÷ Annual grant contribution
A53: F. Financial Returns: NPV / IRR / Payback Period
A54: - | B54: Parameter | C54: Model 1 (3rd Party IPP) | D54: Model 2 (KDKMP owns PLTS) | E54: Model 3 (KDKMP owns PLTS and Productive Assets) | F54: Notes
A55: - | B55: Project lifetime (years) | C55: 20 | D55: 20 | E55: 20 | F55: years | Default 20yr for PLTS system | G55: belum terkoneksi dengan DCF helper table yang fix 20 tahun
A56: - | B56: Discount rate / cost of capital (WACC) | C56: 0.1 | D56: 0.1 | E56: 0.1 | F56: ratio | 10% = typical hurdle rate for rural energy Indonesia
A57: - | B57: Annual revenue growth rate | C57: 0.03 | D57: 0.03 | E57: 0.03 | F57: ratio | 3% conservative pa growth
A58: - | B58: PLTS degradation per year | C58: 0.005 | D58: 0.005 | E58: 0.005 | F58: ratio | 0.5%/yr PV module degradation
A59: - | B59: BESS replacement year | C59: 10 | D59: 10 | E59: 10 | F59: year | LFP battery target replacement cycle
A60: - | B60: BESS replacement cost (Rp juta) | C60: 0 | D60: ='💰 Kapasitas & Investasi'!J70*0.5 | E60: ='💰 Kapasitas & Investasi'!J70*0.5 | F60: Rp juta ← 50% of original BESS CAPEX (Model 1=0, IPP bears)
A61: - | B61: Year 1 Net Cash Flow (Rp juta) | C61: =C48 | D61: =D48 | E61: =E48 | F61: Rp juta ← Annual net income (constant money basis)
A62: - | B62: Simple Payback Period (years) | C62: =IFERROR(IF(C61>0,C34/C61,"N/A"),"N/A") | D62: =IFERROR(IF(D61>0,D34/D61,"N/A"),"N/A") | E62: =IFERROR(IF(E61>0,E34/E61,"N/A"),"N/A") | F62: years ← Net CAPEX after grant ÷ Yr1 Net Income
A63: - | B63: NPV @ discount rate (Rp juta) | C63: =IFERROR(IF(C56<>C57,C61*(1-(1+C57)^C55*(1+C56)^(-C55))/(C56-C57)-C60/(1+C56)^C59-C34,C61*C55*(1+C56)^(-1)-C60/(1+C56)^C59-C34),"Error") | D63: =IFERROR(IF(D56<>D57,D61*(1-(1+D57)^D55*(1+D56)^(-D55))/(D56-D57)-D60/(1+D56)^D59-D34,D61*D55*(1+D56)^(-1)-D60/(1+D56)^D59-D34),"Error") | E63: =IFERROR(IF(E56<>E57,E61*(1-(1+E57)^E55*(1+E56)^(-E55))/(E56-E57)-E60/(1+E56)^E59-E34,E61*E55*(1+E56)^(-1)-E60/(1+E56)^E59-E34),"Error") | F63: Rp juta ← Growing annuity formula; BESS replacement PV deducted
A64: - | B64: IRR (DCF array method) | C64: =IFERROR(C133,"N/A") | D64: =IFERROR(D133,"N/A") | E64: =IFERROR(E133,"N/A") | F64: % ← =IRR(Yr0:Yr20 cash flow array, 10% guess); see DCF helper table rows 125–131 below for full year-by-year breakdown
A66: G. MODEL COMPARISON SUMMARY — Key Metrics at a Glance
A67: - | B67: Parameter | C67: Model 1 (3rd Party IPP) | D67: Model 2 (KDKMP owns PLTS) | E67: Model 3 (KDKMP owns PLTS and Productive Assets) | F67: Notes
A68: - | B68: Total KDKMP CAPEX (Rp juta) | C68: =C32 | D68: =D32 | E68: =E32 | F68: Lower = less equity burden on KDKMP
A69: - | B69: Net CAPEX after Grant (Rp juta) | C69: =C34 | D69: =D34 | E69: =E34 | F69: Remaining KDKMP equity requirement
A70: - | B70: Annual Total Revenue (Rp juta/yr) | C70: =C47 | D70: =D47 | E70: =E47 | F70: Higher is better
A71: - | B71: Annual Total OPEX (Rp juta/yr) | C71: =C43 | D71: =D43 | E71: =E43 | F71: Lower is better
A72: - | B72: Annual Net Income (Rp juta/yr) | C72: =C48 | D72: =D48 | E72: =E48 | F72: Must be positive for viability
A73: - | B73: Simple Payback (years) | C73: =C62 | D73: =D62 | E73: =E62 | F73: Target: < 10 years
A74: - | B74: NPV (Rp juta) | C74: =C63 | D74: =D63 | E74: =E63 | F74: Positive = project is viable at WACC
A75: - | B75: IRR (DCF method) | C75: =C64 | D75: =D64 | E75: =E64 | F75: Compare to 10% hurdle rate
A76: - | B76: Grant Recovery (years) | C76: =C51 | D76: =D51 | E76: =E51 | F76: Shorter = grant recycled faster
A77: - | B77: KDKMP Institutional Burden | C77: Rendah (Low) | D77: Tinggi (High) | E77: Sangat Tinggi (Very High) | F77: Model 1 easiest to manage
A79: B2. DETAIL PENDAPATAN EaaS PER AKTIVITAS — Model 3 Only (Energy as a Service)
B80: 🟨 Kuning = INPUT (ubah sesuai survei harga pasar lokal) | 🟩 Hijau = KALKULASI otomatis | Kolom 'Aktif': linked dari sheet 🐟 Kalkulator (F column). Aktivitas ditagih hanya jika volume > 0 dan flag aktif = 1.
B81: MODEL EaaS: KDKMP menarik biaya layanan (bukan tarif listrik) per unit output yang dihasilkan. Harga mencerminkan nilai layanan kepada pengguna, bukan biaya kWh. Contoh: harga es = Rp/ton es diproduksi (bukan Rp/kWh listrik untuk produksi es).
B82: AP | C82: Layanan EaaS | D82: Volume/Tahun 🟩 (kalkulasi) | E82: Satuan Layanan | F82: Utilisasi 🟨 (% demand terpenuhi) | G82: Harga per Satuan 🟨 (Rp) | H82: Pendapatan (Rp juta/thn) 🟩 | I82: Aktif? (linked 🐟) | K82: Sumber Harga & Catatan
B83: ── FASE 1: PRA-PENANGKAPAN
B84: AP1 | C84: Pengisian baterai perahu (charging station) | D84: ='🐟 Kalkulator Kebutuhan Listrik'!E28 | E84: kWh charged | F84: 0.8 | G84: 2000 | H84: =IF('🐟 Kalkulator Kebutuhan Listrik'!F28=1,D84*F84*G84/1000000,0) | I84: ='🐟 Kalkulator Kebutuhan Listrik'!F28 | K84: Rp 2,000/kWh = harga listrik ke nelayan + margin layanan charging. SPLU PLN = Rp...
B85: AP2 | C85: Sewa set LED fish attractor (per trip) | D85: =IF('🐟 Kalkulator Kebutuhan Listrik'!C13>0,IFERROR('🐟 Kalkulator Kebutuhan Listrik'!C6*'💰 Kapasitas & Investasi'!E9,0),0) | E85: trip pakai | F85: 0.7 | G85: 10000 | H85: =IF('🐟 Kalkulator Kebutuhan Listrik'!F29=1,D85*F85*G85/1000000,0) | I85: ='🐟 Kalkulator Kebutuhan Listrik'!F29 | K85: Rp 10,000/trip pakai set LED per kapal. Alternatif: sewa tahunan Rp 500,000/kapa...
B86: AP3 | C86: Sewa peralatan navigasi & fish finder | D86: =IF('🐟 Kalkulator Kebutuhan Listrik'!C13>0,IFERROR('💰 Kapasitas & Investasi'!E8*1,0),0) | E86: unit-tahun | F86: 0.6 | G86: 1500000 | H86: =IF('🐟 Kalkulator Kebutuhan Listrik'!F30=1,D86*F86*G86/1000000,0) | I86: ='🐟 Kalkulator Kebutuhan Listrik'!F30 | K86: Rp 1,500,000/unit/tahun = sewa GPS + echosounder per kapal. Alternatif: jual uni...
B87: ── FASE 2: PENDARATAN & PELELANGAN (TPI)
B88: AP4 | C88: Biaya pakai fasilitas TPI & dermaga (per landing) | D88: ='🐟 Kalkulator Kebutuhan Listrik'!C13*1000/'💰 Kapasitas & Investasi'!E8 | E88: trip pendaratan | F88: 0.85 | G88: 15000 | H88: =IF('🐟 Kalkulator Kebutuhan Listrik'!F32=1,D88*F88*G88/1000000,0) | I88: ='🐟 Kalkulator Kebutuhan Listrik'!F32 | K88: Rp 15,000/trip pendaratan = retribusi TPI per kapal. Retribusi TPI resmi = 1-3% ...
B89: AP5 | C89: Jasa timbang & sortir (per ton ikan) | D89: ='🐟 Kalkulator Kebutuhan Listrik'!C13 | E89: ton ditimbang | F89: 0.9 | G89: 25000 | H89: =IF('🐟 Kalkulator Kebutuhan Listrik'!F33=1,D89*F89*G89/1000000,0) | I89: ='🐟 Kalkulator Kebutuhan Listrik'!F33 | K89: Rp 25,000/ton = jasa timbang + sortir mekanis. Manual sorting: Rp 15,000–20,000/...
B90: ── FASE 3: PENANGANAN & PENDINGINAN
B91: AP6 | C91: Penjualan es ke nelayan & pemroses ikan | D91: ='🐟 Kalkulator Kebutuhan Listrik'!C18 | E91: ton es | F91: 0.85 | G91: 700000 | H91: =IF('🐟 Kalkulator Kebutuhan Listrik'!F35=1,D91*F91*G91/1000000,0) | I91: ='🐟 Kalkulator Kebutuhan Listrik'!F35 | K91: Rp 700,000/ton es = harga jual es balok/es curah. Harga es di Indonesia (2024): ...
B92: AP7 | C92: Sewa cold storage (per ton per hari) | D92: ='🐟 Kalkulator Kebutuhan Listrik'!C13*'💰 Kapasitas & Investasi'!E16 | E92: ton-hari | F92: 0.8 | G92: 7000 | H92: =IF('🐟 Kalkulator Kebutuhan Listrik'!F36=1,D92*F92*G92/1000000,0) | I92: ='🐟 Kalkulator Kebutuhan Listrik'!F36 | K92: Rp 7,000/ton/hari = tarif sewa cold storage. Cold storage Indonesia (2024): Gu...
B93: AP8 | C93: Jasa blast freezing (per ton ikan) | D93: ='🐟 Kalkulator Kebutuhan Listrik'!C13 | E93: ton dibekukan | F93: 0.7 | G93: 250000 | H93: =IF('🐟 Kalkulator Kebutuhan Listrik'!F37=1,D93*F93*G93/1000000,0) | I93: ='🐟 Kalkulator Kebutuhan Listrik'!F37 | K93: Rp 250,000/ton = jasa blast freezing ke -18°C hingga -35°C. Tarif blast freezing...
B94: ── FASE 4: PENGOLAHAN IKAN (OPSIONAL — nilai tambah)
B95: AP9 | C95: Jasa fillet ikan (per kg input) | D95: ='🐟 Kalkulator Kebutuhan Listrik'!C13*1000 | E95: kg ikan diproses | F95: 0.65 | G95: 500 | H95: =IF('🐟 Kalkulator Kebutuhan Listrik'!F39=1,D95*F95*G95/1000000,0) | I95: ='🐟 Kalkulator Kebutuhan Listrik'!F39 | K95: Rp 500/kg = biaya jasa fillet (upah + listrik + pisau). Industri pengolahan ikan...
B96: AP10 | C96: Jasa pengeringan ikan (per kg output ikan kering) | D96: ='🐟 Kalkulator Kebutuhan Listrik'!C13*250 | E96: kg ikan kering | F96: 0.6 | G96: 5000 | H96: =IF('🐟 Kalkulator Kebutuhan Listrik'!F40=1,D96*F96*G96/1000000,0) | I96: ='🐟 Kalkulator Kebutuhan Listrik'!F40 | K96: Rp 5,000/kg ikan kering = upah jasa + listrik + kemasan. Harga jasa pengeringan ...
B97: AP11 | C97: Jasa vakum/pengemasan (per kg produk) | D97: ='🐟 Kalkulator Kebutuhan Listrik'!C13*1000 | E97: kg dikemas | F97: 0.65 | G97: 300 | H97: =IF('🐟 Kalkulator Kebutuhan Listrik'!F41=1,D97*F97*G97/1000000,0) | I97: ='🐟 Kalkulator Kebutuhan Listrik'!F41 | K97: Rp 300/kg = biaya jasa vakum + kemasan plastik. Mesin vakum skala UMKM Indonesia...
B98: ── FASE 5: AIR BERSIH & FASILITAS PENDUKUNG
B99: AP12 | C99: Jasa penyediaan air bersih (per m³ dipompa) | D99: =('🐟 Kalkulator Kebutuhan Listrik'!C13*'💰 Kapasitas & Investasi'!E19)+('🐟 Kalkulator Kebutuhan Listrik'!C18*'💰 Kapasitas & Investasi'!E20) | E99: m³/tahun | F99: 0.9 | G99: 1500 | H99: =IF('🐟 Kalkulator Kebutuhan Listrik'!F43=1,D99*F99*G99/1000000,0) | I99: ='🐟 Kalkulator Kebutuhan Listrik'!F43 | K99: Rp 1,500/m³ = tarif air bersih untuk pengolahan ikan. Tarif air PDAM komersial I...
B100: AP13 | C100: Jasa aerasi kolam ikan hidup (per hari operasi) | D100: =IF('🐟 Kalkulator Kebutuhan Listrik'!C13>0,'💰 Kapasitas & Investasi'!E6,0) | E100: hari operasi | F100: 0.75 | G100: 100000 | H100: =IF('🐟 Kalkulator Kebutuhan Listrik'!F44=1,D100*F100*G100/1000000,0) | I100: ='🐟 Kalkulator Kebutuhan Listrik'!F44 | K100: Rp 100,000/hari = tarif sewa aerasi kolam (listrik + operator). Setara Rp 36 jut...
B101: AP14 | C101: Biaya fasilitas pengolahan (per hari pakai) | D101: =IF('🐟 Kalkulator Kebutuhan Listrik'!C13>0,'💰 Kapasitas & Investasi'!E6,0) | E101: hari pakai | F101: 0.8 | G101: 50000 | H101: =IF('🐟 Kalkulator Kebutuhan Listrik'!F45=1,D101*F101*G101/1000000,0) | I101: ='🐟 Kalkulator Kebutuhan Listrik'!F45 | K101: Rp 50,000/hari = biaya sewa fasilitas (termasuk penerangan + air). Fasilitas pro...
B102: ── FASE 6: DISTRIBUSI & PENJUALAN
B103: AP15 | C103: Jasa distribusi berpendingin (per trip pengiriman) | D103: =IFERROR('🐟 Kalkulator Kebutuhan Listrik'!C19*'💰 Kapasitas & Investasi'!E6,0) | E103: trip pengiriman | F103: 0.65 | G103: 200000 | H103: =IF('🐟 Kalkulator Kebutuhan Listrik'!F47=1,D103*F103*G103/1000000,0) | I103: ='🐟 Kalkulator Kebutuhan Listrik'!F47 | K103: Rp 200,000/trip = biaya distribusi dengan kendaraan berpendingin. Tarif angkutan...
B104: AP16 | C104: Sewa display chiller kios/pasar (per hari per unit) | D104: =IF('🐟 Kalkulator Kebutuhan Listrik'!C13>0,2*365,0) | E104: unit-hari | F104: 0.7 | G104: 75000 | H104: =IF('🐟 Kalkulator Kebutuhan Listrik'!F48=1,D104*F104*G104/1000000,0) | I104: ='🐟 Kalkulator Kebutuhan Listrik'!F48 | K104: Rp 75,000/unit/hari = sewa display chiller showcase. Tarif sewa showcase chiller...
B105: TOTAL PENDAPATAN EaaS PER AKTIVITAS (Rp juta/tahun) | H105: =H84+H85+H86+H88+H89+H91+H92+H93+H95+H96+H97+H99+H100+H101+H103+H104
B107: Kontribusi per aktivitas terhadap total EaaS revenue (Model 3):
A108: — | B108: AP | C108: Layanan | D108: Rev (Rp juta) | E108: % dari Total
B109: AP1 | C109: Charging baterai | D109: =H84 | E109: =IFERROR(H84/H105,0)
...

Sheet Summary & Graphs
A1: Rangkuman
A3: Perhitungan Pendapatan KDKMP (Rp juta/tahun) | B3: Model 1 | C3: Model 2 | D3: Model 3
A4: Penjualan listrik ke anggota koperasi | B4: ='Kalkulator Pendapatan'!C16 | C4: ='Kalkulator Pendapatan'!D16 | D4: ='Kalkulator Pendapatan'!E16
A5: Penjualan listrik ke PLN | B5: ='Kalkulator Pendapatan'!C17 | C5: ='Kalkulator Pendapatan'!D17 | D5: ='Kalkulator Pendapatan'!E17
A6: EaaS | B6: ='Kalkulator Pendapatan'!C26 | C6: ='Kalkulator Pendapatan'!D26 | D6: ='Kalkulator Pendapatan'!E26
A8: Kapasitas PLTS dan BESS KDKMP | B8: Model 1 | C8: Model 2 | D8: Model 3
A9: PLTS (kWp) | B9: =ROUNDUP('🐟 Kalkulator Kebutuhan Listrik'!$D$60,0) | C9: =ROUNDUP('🐟 Kalkulator Kebutuhan Listrik'!$D$63,0) | D9: =ROUNDUP('🐟 Kalkulator Kebutuhan Listrik'!$D$60,0)
A10: BESS (kWh) | B10: =ROUNDUP('🐟 Kalkulator Kebutuhan Listrik'!$D$61,0) | C10: =ROUNDUP('🐟 Kalkulator Kebutuhan Listrik'!$D$61,0) | D10: =ROUNDUP('🐟 Kalkulator Kebutuhan Listrik'!$D$61,0)
A12: Perhitungan CAPEX KDKMP (Rp miliar) | B12: Model 1 | C12: Model 2 | D12: Model 3
A13: CAPEX infrastruktur PLTS + BESS | B13: ='Kalkulator Pendapatan'!C30/1000 | C13: ='Kalkulator Pendapatan'!D30/1000 | D13: ='Kalkulator Pendapatan'!E30/1000
A14: CAPEX aset ekonomi produktif | B14: ='Kalkulator Pendapatan'!C31/1000 | C14: ='Kalkulator Pendapatan'!D31/1000 | D14: ='Kalkulator Pendapatan'!E31/1000
A16: Perhitungan OPEX KDKMP (Rp juta/tahun) | B16: Model 1 | C16: Model 2 | D16: Model 3
A17: OPEX infrastruktur PLTS + BESS | B17: ='Kalkulator Pendapatan'!C39 | C17: ='Kalkulator Pendapatan'!D39 | D17: ='Kalkulator Pendapatan'!E39
A18: OPEX aset ekonomi produktif | B18: ='Kalkulator Pendapatan'!C41 | C18: ='Kalkulator Pendapatan'!D41 | D18: ='Kalkulator Pendapatan'!E41
A19: Biaya staf dan manajemen KDKMP | B19: ='Kalkulator Pendapatan'!C42 | C19: ='Kalkulator Pendapatan'!D42 | D19: ='Kalkulator Pendapatan'!E42
A21: Payback Period | B21: Model 1 | C21: Model 2 | D21: Model 3
A22: Payback Period (tahun) | B22: ='Kalkulator Pendapatan'!C73 | C22: ='Kalkulator Pendapatan'!D73 | D22: ='Kalkulator Pendapatan'!E73
A24: IRR | B24: Model 1 | C24: Model 2 | D24: Model 3
A25: IRR | B25: ='Kalkulator Pendapatan'!C64 | C25: ='Kalkulator Pendapatan'!D64 | D25: ='Kalkulator Pendapatan'!E64
A27: Tarif listrik ke pelanggan (Rp/kWh) | B27: Model 1 | C27: Model 2 | D27: Model 3
A28: Tarif listrik ke pelanggan (Rp/kWh) | B28: ='Kalkulator Pendapatan'!C6 | C28: ='Kalkulator Pendapatan'!D9 | D28: ='Kalkulator Pendapatan'!E6
A30: Total subsidi pemerintah pusat (Rp juta/tahun) | B30: Model 1 | C30: Model 2 | D30: Model 3 | E30: Note
A31: Tambahan subsidi listrik ke PLN | B31: ='Kalkulator Pendapatan'!C11*'Kalkulator Pendapatan'!C14/1000000 | C31: ='Kalkulator Pendapatan'!D11*'Kalkulator Pendapatan'!D14/1000000 | D31: ='Kalkulator Pendapatan'!E11*'Kalkulator Pendapatan'!E14/1000000 | E31: subsidi hanya untuk anggota koperasi, subsidi untuk surplus yang dijual di luar scope
A32: Subsidi infrastruktur PLTS ke KDKMP | B32: ='Kalkulator Pendapatan'!C19 | C32: ='Kalkulator Pendapatan'!D19 | D32: ='Kalkulator Pendapatan'!E19
A33: Subsidi infrastruktur aset produktif ke KDKMP | B33: ='Kalkulator Pendapatan'!C25 | C33: ='Kalkulator Pendapatan'!D25 | D33: ='Kalkulator Pendapatan'!E25
A35: Kebutuhan listrik KDKMP (sama untuk seluruh model) (MWh/tahun)
A36: Parameter | B36: Kebutuhan Listrik
A37: Kebutuhan listrik rumah tangga tahunan | B37: ='🐟 Kalkulator Kebutuhan Listrik'!D58/1000
A38: Kebutuhan listrik komoditas ikan (termasuk es untuk aktivitas produksi ikan) | B38: ='🐟 Kalkulator Kebutuhan Listrik'!D55/1000
A39: Kebutuhan listrik komoditas es (dijual ke luar) | B39: ='🐟 Kalkulator Kebutuhan Listrik'!D56/1000
A40: Total | B40: =SUM(B37:B39)
A42: Pendapatan dari komoditas (sama untuk seluruh model)
A43: Komoditas | B43: Rp miliar/tahun
A44: Fish | B44: ='🐟 Kalkulator Kebutuhan Listrik'!C11/1000
A45: Es (dijual ke nelayan lokal) | B45: ='🐟 Kalkulator Kebutuhan Listrik'!C22/1000
A46: Es (dijual ke luar) | B46: ='🐟 Kalkulator Kebutuhan Listrik'!C23/1000
A47: Total | B47: =SUM(B44:B46)
